{
  "weekly": {
    "tasksCompleted": 0,
    "tasksCreated": 0,
    "averageCompletionRate": 0,
    "criticalTasksCompleted": 0,
    "highPriorityCompletionRate": 0,
    "mostCommonPriority": "medium",
    "bestDay": {
      "date": "2026-06-21",
      "completionRate": 0
    },
    "worstDay": {
      "date": "2026-06-21",
      "completionRate": 0
    }
  },
  "monthly": {
    "tasksCompleted": 6,
    "tasksCreated": 10,
    "averageCompletionRate": 7,
    "criticalTasksCompleted": 0,
    "highPriorityCompletionRate": 0,
    "mostCommonPriority": "medium"
  },
  "contributorTrends": {
    "weeklyLeaderboard": [],
    "monthlyLeaderboard": [
      {
        "username": "kamali-sree",
        "joinedTasks": 4,
        "completedTasks": 6
      }
    ],
    "allTimeLeaderboard": [
      {
        "username": "kamali-sree",
        "joinedTasks": 4,
        "completedTasks": 6
      }
    ]
  }
}
